LICENSE
README.rst
setup.py
xextension/__init__.py
xextension/app.py
xextension.egg-info/PKG-INFO
xextension.egg-info/SOURCES.txt
xextension.egg-info/dependency_links.txt
xextension.egg-info/top_level.txt