Metadata-Version: 2.1
Name: xextension
Version: 0.0.2
Summary: utils for python
Home-page: https://github.com/me/myproject
Author: yacyet
Author-email: wooxiaodong@foxmail.com
License: MIT
Platform: UNKNOWN
Classifier: License :: OSI Approved :: MIT License
Classifier: Programming Language :: Python
Classifier: Programming Language :: Python :: 3
Classifier: Programming Language :: Python :: 3.6
Classifier: Programming Language :: Python :: Implementation :: CPython
Classifier: Programming Language :: Python :: Implementation :: PyPy
Requires-Python: >=3.6.0
License-File: LICENSE
